README.rst
setup.py
pythonwpy/__init__.py
pythonwpy/__main__.py
pythonwpy.egg-info/PKG-INFO
pythonwpy.egg-info/SOURCES.txt
pythonwpy.egg-info/dependency_links.txt
pythonwpy.egg-info/entry_points.txt
pythonwpy.egg-info/top_level.txt