Metadata-Version: 1.0
Name: pythonwpy
Version: 0.4.1
Summary: python -c, with tab completion and shorthand
Home-page: https://github.com/Russell91/pythonwpy
Author: UNKNOWN
Author-email: UNKNOWN
License: MIT
Platform: UNKNOWN
